Dual Port /True Dual Port/sram_dp.v
// This is a code for True dual port SRAM sync read

module sram_dp #(
    parameter depth =8,
    parameter width = 8
) (
    input [width-1:0] data_inA,data_inB,
    input clk_A,clk_B, we_A, we_B, re_A, re_B, cs,
    input [$clog2(depth)-1:0]add_A, add_B,
    output reg [width-1:0]data_outA, data_outB
);
    // the first notable difference is that all the signal clk, output, input and address everything is different
    // that is because now Port A and Port B are truely 2 different ports working simultaneoulsy
    // if you want async read then declare data_outB as just output not reg
    
    reg [width-1:0] mem [0:depth-1];  
    // the memory array remains the same just the ports now are different
    // This is for Port A
    always @(posedge clk_A) begin
        if (cs && we_A) begin
            mem[add_A] <= data_inA;
        end else begin
            if (cs && re_A) begin
                data_outA <= mem[add_A];
            end else begin
                data_outA <= 'bz; 
            end
        end
    end 

    // This is for port B
    always @(posedge clk_B) begin
        if (cs && we_B) begin
            mem[add_B] <= data_inB;
        end else begin
            if (cs && re_B) begin
                data_outB<= mem[add_B];
            end else begin
                data_outB <= 'bz; 
            end
        end
    end
    // again if you remove the read enable signals out of the clocked always block and do a blocking assignment
    // this same code will become asynchoronus read true dual port SRAM
endmodule

Dual Port /True Dual Port/sram_dp_tb.v
`timescale 1ns/1ps
`include "sram_dp.v"

module sram_dp_tb;

    parameter depth = 256;
    parameter width = 16;

    reg [width-1:0] data_inA, data_inB;
    reg [$clog2(depth)-1:0] add_A, add_B;
    reg clk_A = 0, clk_B = 0;
    reg we_A = 0, we_B = 0, re_A = 0, re_B = 0, cs = 0;
    wire [width-1:0] data_outA, data_outB;

    sram_dp #(depth, width) DUT (
        .data_inA(data_inA),
        .data_inB(data_inB),
        .clk_A(clk_A),
        .clk_B(clk_B),
        .we_A(we_A),
        .we_B(we_B),
        .re_A(re_A),
        .re_B(re_B),
        .cs(cs),
        .add_A(add_A),
        .add_B(add_B),
        .data_outA(data_outA),
        .data_outB(data_outB)
    );

    // Clock generation
    always #5 clk_A = ~clk_A;
    always #7 clk_B = ~clk_B;

    initial begin
        $dumpfile("sram_dp_tb.vcd");
        $dumpvars(0,sram_dp_tb);
    end

    initial begin
        $display("Time\tclk_A clk_B | we_A re_A add_A data_inA | we_B re_B add_B data_inB || data_outA data_outB");
        $monitor("%4t\t%b     %b    |  %b    %b    %3d    %h   |  %b    %b    %3d    %h   ||   %h       %h",
                 $time, clk_A, clk_B,
                 we_A, re_A, add_A, data_inA,
                 we_B, re_B, add_B, data_inB,
                 data_outA, data_outB);

        // Initialize
        cs = 1;

        // Write to Port A @ addr 5
        @(negedge clk_A);
        data_inA = 16'hAAAA;
        add_A = 5;
        we_A = 1; re_A = 0;

        // Write to Port B @ addr 10
        @(negedge clk_B);
        data_inB = 16'hBBBB;
        add_B = 10;
        we_B = 1; re_B = 0;

        // Disable writes
        @(negedge clk_A); we_A = 0;
        @(negedge clk_B); we_B = 0;

        // Read back from Port A @ addr 5
        @(negedge clk_A);
        add_A = 5;
        re_A = 1;

        // Read back from Port B @ addr 10
        @(negedge clk_B);
        add_B = 10;
        re_B = 1;

        // Simultaneous write from A and read from B
        @(negedge clk_A);
        data_inA = 16'h1234;
        add_A = 15;
        we_A = 1; re_A = 0;

        @(negedge clk_B);
        add_B = 5;
        re_B = 1; // Should read 0xAAAA from earlier write

        @(negedge clk_A);
        we_A = 0;

        // Final read to verify last write
        @(negedge clk_A);
        add_A = 15;
        re_A = 1;

        @(negedge clk_B);
        re_B = 0;

        #20;
        $finish;
    end
endmodule

Dual Port /True Dual Port/sram_dp_tb.vcd
$date
	Sat Aug 02 22:24:46 2025
$end
$version
	Icarus Verilog
$end
$timescale
	1ps
$end
$scope module sram_dp_tb $end
$var wire 16 ! data_outA [15:0] $end
$var wire 16 " data_outB [15:0] $end
$var reg 8 # add_A [7:0] $end
$var reg 8 $ add_B [7:0] $end
$var reg 1 % clk_A $end
$var reg 1 & clk_B $end
$var reg 1 ' cs $end
$var reg 16 ( data_inA [15:0] $end
$var reg 16 ) data_inB [15:0] $end
$var reg 1 * re_A $end
$var reg 1 + re_B $end
$var reg 1 , we_A $end
$var reg 1 - we_B $end
$scope module DUT $end
$var wire 8 . add_A [7:0] $end
$var wire 8 / add_B [7:0] $end
$var wire 1 0 clk_A $end
$var wire 1 1 clk_B $end
$var wire 1 2 cs $end
$var wire 16 3 data_inA [15:0] $end
$var wire 16 4 data_inB [15:0] $end
$var wire 1 5 re_A $end
$var wire 1 6 re_B $end
$var wire 1 7 we_A $end
$var wire 1 8 we_B $end
$var reg 16 9 data_outA [15:0] $end
$var reg 16 : data_outB [15:0] $end
$upscope $end
$upscope $end
$enddefinitions $end
#0
$dumpvars
bx :
bx 9
08
07
06
05
bx 4
bx 3
12
01
00
bx /
bx .
0-
0,
0+
0*
bx )
bx (
1'
0&
0%
bx $
bx #
bx "
bx !
$end
#5000
bz 9
bz !
1%
10
#7000
bz :
bz "
1&
11
#10000
1,
17
b101 #
b101 .
b1010101010101010 (
b1010101010101010 3
0%
00
#14000
1-
18
b1010 $
b1010 /
b1011101110111011 )
b1011101110111011 4
0&
01
#15000
1%
10
#20000
0,
07
0%
00
#21000
1&
11
#25000
1%
10
#28000
0-
08
0&
01
#30000
1*
15
0%
00
#35000
b1010101010101010 9
b1010101010101010 !
1%
10
1&
11
#40000
0%
00
#42000
1+
16
0&
01
#45000
1%
10
#49000
b1011101110111011 :
b1011101110111011 "
1&
11
#50000
0*
05
1,
17
b1111 #
b1111 .
b1001000110100 (
b1001000110100 3
0%
00
#55000
1%
10
#56000
b101 $
b101 /
0&
01
#60000
0,
07
0%
00
#63000
b1010101010101010 :
b1010101010101010 "
1&
11
#65000
bz 9
bz !
1%
10
#70000
1*
15
0%
00
0&
01
#75000
b1001000110100 9
b1001000110100 !
1%
10
#77000
1&
11
#80000
0%
00
#84000
0+
06
0&
01
#85000
1%
10
#90000
0%
00
#91000
bz :
bz "
1&
11
