Dual Port /Pseudo Dual port/sram_pdp.v
// This is a code for Pseudo dual port SRAM sync read

module sram_pdp #(
    parameter depth =8,
    parameter width = 8
) (
    input [width-1:0] data_inA,
    input clk, we_A, re_B, cs,
    input [$clog2(depth)-1:0]add_A, add_B,
    output reg [width-1:0]data_outB
    // if you want async read then declare data_outB as just output not reg
);
    reg [width-1:0] mem [0:depth-1];
    
// This is for Port A
    always @(posedge clk) begin
        if (cs && we_A) begin
            mem[add_A] <= data_inA;
        end
    end
// This is for port B
    always @(posedge clk) begin // here instead of clk signal, do direct assign for async read operation
        if (cs && re_B) begin
            data_outB <= mem[add_B]; // assign data_outB = re_B ? mem[add_B] : 'bz 
        end else begin
            data_outB <= 'bz;
        end
    end
endmodule

Dual Port /Pseudo Dual port/sram_pdp_tb.v
`timescale 1ns/1ns
`include "sram_pdp.v"

module sram_pdp_tb;

    parameter depth = 1024;
    parameter width = 16;

    reg [width -1:0] A;
    reg clk, w, r, cs;
    reg [$clog2(depth)-1:0] aa, ab;
    wire [width -1:0] y;

    // Instantiate the DUT
    sram_pdp #(.depth(depth), .width(width)) uut1 (
        .data_inA(A), .clk(clk), .we_A(w), .re_B(r), .cs(cs),
        .add_A(aa), .add_B(ab), .data_outB(y)
    );

    // Clock generation
    initial begin
        clk = 0;
        forever #5 clk = ~clk;
    end

    // Stimulus
    initial begin
        // Initialize signals
        A = 0; w = 0; r = 0; cs = 0; aa = 0; ab = 0;

        // Dump waveform
        $dumpfile("sram_pdp_tb.vcd");
        $dumpvars(0, sram_pdp_tb);

        // --- Write Operation ---
        @(posedge clk);
        cs = 1; w = 1; aa = 12; A = 16'hABCD;

        @(posedge clk);
        w = 0; A = 0; // Finish write

        // --- Read Operation ---
        @(posedge clk);
        r = 1; ab = 12;

        @(posedge clk);
        r = 0;

        // --- Second Write ---
        @(posedge clk);
        w = 1; aa = 100; A = 16'h1234;

        @(posedge clk);
        w = 0;

        // --- Second Read ---
        @(posedge clk);
        r = 1; ab = 100;

        @(posedge clk);
        r = 0;

        // --- Done ---
        @(posedge clk);
        $finish;
    end

    // Monitor
    initial begin
        $monitor("Time=%0t | clk=%b | cs=%b | we_A=%b | re_B=%b | A=%h | aa=%d | ab=%d | y=%h",
            $time, clk, cs, w, r, A, aa, ab, y);
    end

endmodule

Dual Port /Pseudo Dual port/sram_pdp_tb.vcd
$date
	Sat Aug 02 20:40:21 2025
$end
$version
	Icarus Verilog
$end
$timescale
	1ns
$end
$scope module sram_pdp_tb $end
$var wire 16 ! y [15:0] $end
$var reg 16 " A [15:0] $end
$var reg 10 # aa [9:0] $end
$var reg 10 $ ab [9:0] $end
$var reg 1 % clk $end
$var reg 1 & cs $end
$var reg 1 ' r $end
$var reg 1 ( w $end
$scope module uut1 $end
$var wire 10 ) add_A [9:0] $end
$var wire 10 * add_B [9:0] $end
$var wire 1 + clk $end
$var wire 1 , cs $end
$var wire 16 - data_inA [15:0] $end
$var wire 1 . re_B $end
$var wire 1 / we_A $end
$var reg 16 0 data_outB [15:0] $end
$upscope $end
$upscope $end
$enddefinitions $end
#0
$dumpvars
bx 0
0/
0.
b0 -
0,
0+
b0 *
b0 )
0(
0'
0&
0%
b0 $
b0 #
b0 "
bx !
$end
#5
bz 0
bz !
b1010101111001101 "
b1010101111001101 -
b1100 #
b1100 )
1(
1/
1&
1,
1%
1+
#10
0%
0+
#15
b0 "
b0 -
0(
0/
1%
1+
#20
0%
0+
#25
b1010101111001101 0
b1010101111001101 !
b1100 $
b1100 *
1'
1.
1%
1+
#30
0%
0+
#35
0'
0.
1%
1+
#40
0%
0+
#45
bz 0
bz !
b1001000110100 "
b1001000110100 -
b1100100 #
b1100100 )
1(
1/
1%
1+
#50
0%
0+
#55
0(
0/
1%
1+
#60
0%
0+
#65
b1001000110100 0
b1001000110100 !
b1100100 $
b1100100 *
1'
1.
1%
1+
#70
0%
0+
#75
0'
0.
1%
1+
#80
0%
0+
#85
bz 0
bz !
1%
1+
