Synchronous_SRAM/sram_sp.v
// This sram code is parameterized as it is for sync read not async read
module sram_sp #(
    parameter depth = 8 ,
    parameter width = 4
) (
    input  [width-1:0] data_in,
    input clk, we,re,
    input [$clog2(depth)-1:0] add,
    output reg [width-1:0] data_out // this is sync read, if this was not reg then assign statement after always block and this becomes async
// this is sync read, if this was not reg then assign statement after always block and this becomes async
);
    reg [width-1:0]mem[0:depth-1];
    
    always @(posedge clk) begin
        if(we) begin
            mem[add] <= data_in;
        end if (re) begin
            data_out <= mem[add]; // this is sync read 
        end else begin
            data_out <= 'bz; 
        end
    end
endmodule

Synchronous_SRAM/sram_sp_tb.v
`timescale 1ns/1ns
`include "sram_sp.v"

module sram_sp_tb;

    parameter depth = 10;
    parameter width = 8;

    reg [width-1 : 0] data_in;
    reg [$clog2(depth)-1:0] add;
    reg clk, re, we;
    wire [width-1:0] data_out;

    sram_sp #(.depth(depth) , .width(width)) uut1 (.data_in(data_in), .clk(clk), .re(re), .we(we), .add(add),  .data_out(data_out));

    initial begin
        clk =0;
        forever begin
        #5 clk = ~clk;
        end
    end


    initial begin
        data_in = 0;
        add = 0;
        re = 0; we = 0;

        $dumpfile("sram_sp_tb.vcd");
        $dumpvars(0, sram_sp_tb);

        // Write 25 to address 0
        #10;
        data_in = 8'd25;
        add = 0;
        we = 1;

        #10;
        we = 0;

        // Read from address 0
        #10;
        re = 1;

        #10;
        re = 0;

        // Finish simulation
        #10;
        $finish;
    end

    initial begin
        $monitor("time = %0t | addr = %d | data_in = %d | data_out = %d | we = %b | re = %b",
                 $time, add, data_in, data_out, we, re);
    end



endmodule

Synchronous_SRAM/sram_sp_tb.vcd
$date
	Sat Aug 02 02:56:36 2025
$end
$version
	Icarus Verilog
$end
$timescale
	1ns
$end
$scope module sram_sp_tb $end
$var wire 8 ! data_out [7:0] $end
$var reg 4 " add [3:0] $end
$var reg 1 # clk $end
$var reg 8 $ data_in [7:0] $end
$var reg 1 % re $end
$var reg 1 & we $end
$scope module uut1 $end
$var wire 4 ' add [3:0] $end
$var wire 1 ( clk $end
$var wire 8 ) data_in [7:0] $end
$var wire 1 * re $end
$var wire 1 + we $end
$var reg 8 , data_out [7:0] $end
$upscope $end
$upscope $end
$enddefinitions $end
#0
$dumpvars
bx ,
0+
0*
b0 )
0(
b0 '
0&
0%
b0 $
0#
b0 "
bx !
$end
#5
bz ,
bz !
1#
1(
#10
0#
0(
1&
1+
b11001 $
b11001 )
#15
1#
1(
#20
0#
0(
0&
0+
#25
1#
1(
#30
0#
0(
1%
1*
#35
b11001 ,
b11001 !
1#
1(
#40
0#
0(
0%
0*
#45
bz ,
bz !
1#
1(
